{"cameraMode":{"drawMode":0,"name":"Shaded","section":"Shading Mode"},"sceneLighting":true,"audioPlay":false,"sceneViewState":{"m_AlwaysRefresh":false,"showFog":true,"showSkybox":true,"showFlares":true,"showImageEffects":true,"showParticleSystems":true,"showVisualEffectGraphs":true,"m_FxEnabled":true},"in2DMode":false,"pivot":{"x":813.0686645507813,"y":78.39781188964844,"z":513.3071899414063},"rotation":{"x":0.3980461657047272,"y":-0.06430841237306595,"z":0.07084719836711884,"w":0.912643313407898},"size":244.18231201171876,"orthographic":false}